MANIFEST.in
README.txt
setup.py
Datastructures_Algorithms/Arrays.py
Datastructures_Algorithms/BinarySearchTree.py
Datastructures_Algorithms/LinkedList.py
Datastructures_Algorithms/Queue.py
Datastructures_Algorithms/Sorting.py
Datastructures_Algorithms/Stack.py
Datastructures_Algorithms/__init__.py
Datastructures_Algorithms.egg-info/PKG-INFO
Datastructures_Algorithms.egg-info/SOURCES.txt
Datastructures_Algorithms.egg-info/dependency_links.txt
Datastructures_Algorithms.egg-info/top_level.txt