Metadata-Version: 1.1
Name: Datastructures-Algorithms
Version: 0.0.1
Summary: Implementation of data structures and algorithms in python
Home-page: https://github.com/ayushsingh5941
Author: Ayush Singh
Author-email: ayushsingh5941@gmail.com
License: MIT
Keywords: Data Structures,Algorithms
Platform: UNKNOWN
Classifier: Development Status :: 5 - Production/Stable
Classifier: Intended Audience :: Education
Classifier: Operating System :: Microsoft :: Windows :: Windows 10
Classifier: License :: OSI Approved :: MIT License
Classifier: Programming Language :: Python :: 3
